cfx_brownie/__init__.py
cfx_brownie/_cli.py
conflux_web3py_signer/__init__.py
conflux_web3py_signer/hacked_signing.py
conflux_web3py_signer/hook_brownie.py
conflux_web3py_signer/hook_web3.py
conflux_web3py_signer/py.typed
conflux_web3py_signer-1.0.0b3.dist-info/METADATA
conflux_web3py_signer-1.0.0b3.dist-info/WHEEL
conflux_web3py_signer-1.0.0b3.dist-info/entry_points.txt
conflux_web3py_signer-1.0.0b3.dist-info/top_level.txt
conflux_web3py_signer-1.0.0b3.dist-info/RECORD
