Metadata-Version: 2.1
Name: conflux-web3py-signer
Version: 1.0.0b3
Summary: Plugin to monkey patch web3.py to support cfx2eth-bridge
Home-page: https://github.com/conflux-fans/conflux-web3py-signer
Author: Conflux-Dev
Author-email: wenda.zhang@confluxnetwork.org
Keywords: python,conflux,blockchain
Classifier: Programming Language :: Python :: 3
Classifier: Programming Language :: Python :: 3.7
Classifier: Programming Language :: Python :: 3.8
Classifier: Programming Language :: Python :: 3.9
Classifier: Programming Language :: Python :: 3.10
Classifier: Operating System :: MacOS :: MacOS X
Classifier: Operating System :: Microsoft :: Windows
Requires-Dist: cfx-account (>=1.0.0)
Requires-Dist: web3 (>=5.30)
Provides-Extra: brownie
Requires-Dist: eth-brownie (==1.19.2) ; extra == 'brownie'
Provides-Extra: dev
Requires-Dist: pytest (<7,>=6.2.5) ; extra == 'dev'
Requires-Dist: typing-extensions ; extra == 'dev'
Requires-Dist: brownie ; extra == 'dev'
Requires-Dist: black (<23.0,>=22.1.0) ; extra == 'dev'
Requires-Dist: wheel ; extra == 'dev'
Requires-Dist: bumpversion ; extra == 'dev'
Provides-Extra: docs
Requires-Dist: wheel ; extra == 'docs'
Provides-Extra: linter
Requires-Dist: black (<23.0,>=22.1.0) ; extra == 'linter'
Provides-Extra: tester
Requires-Dist: pytest (<7,>=6.2.5) ; extra == 'tester'
Requires-Dist: typing-extensions ; extra == 'tester'
Requires-Dist: brownie ; extra == 'tester'
